py_aws_core/__init__.py
py_aws_core/boto_clients.py
py_aws_core/boto_responses.py
py_aws_core/clients.py
py_aws_core/cognito_api.py
py_aws_core/const.py
py_aws_core/cookies.py
py_aws_core/db_api.py
py_aws_core/db_interface.py
py_aws_core/db_service.py
py_aws_core/decorators.py
py_aws_core/dynamodb_api.py
py_aws_core/dynamodb_entities.py
py_aws_core/encoders.py
py_aws_core/events.py
py_aws_core/exceptions.py
py_aws_core/logs.py
py_aws_core/mixins.py
py_aws_core/router.py
py_aws_core/secrets_interface.py
py_aws_core/secrets_manager.py
py_aws_core/secrets_service.py
py_aws_core/session_interface.py
py_aws_core/spoofing/__init__.py
py_aws_core/spoofing/_tests/__init__.py
py_aws_core/spoofing/_tests/proxyrack/__init__.py
py_aws_core/spoofing/_tests/proxyrack/_resources/active_conns.json
py_aws_core/spoofing/_tests/proxyrack/_resources/cities.json
py_aws_core/spoofing/_tests/proxyrack/_resources/countries.json
py_aws_core/spoofing/_tests/proxyrack/_resources/ipify.json
py_aws_core/spoofing/_tests/proxyrack/_resources/passwords.json
py_aws_core/spoofing/_tests/proxyrack/_resources/stats.json
py_aws_core/spoofing/_tests/proxyrack/_resources/us_isps.json
py_aws_core/spoofing/_tests/proxyrack/const.py
py_aws_core/spoofing/_tests/proxyrack/test_backends.py
py_aws_core/spoofing/_tests/proxyrack/test_proxyrack_api.py
py_aws_core/spoofing/_tests/proxyrack/test_utils.py
py_aws_core/spoofing/const.py
py_aws_core/spoofing/exceptions.py
py_aws_core/spoofing/proxy_interface.py
py_aws_core/spoofing/proxyrack/__init__.py
py_aws_core/spoofing/proxyrack/const.py
py_aws_core/spoofing/proxyrack/exceptions.py
py_aws_core/spoofing/proxyrack/proxyrack_api.py
py_aws_core/spoofing/proxyrack/proxyrack_service.py
py_aws_core/spoofing/proxyrack/utils.py
py_aws_core/ssm_parameter_store.py
py_aws_core/testing.py
py_aws_core/utils.py
py_aws_core-0.2.41.dist-info/LICENSE
py_aws_core-0.2.41.dist-info/METADATA
py_aws_core-0.2.41.dist-info/WHEEL
py_aws_core-0.2.41.dist-info/RECORD
