Metadata-Version: 2.1
Name: py-aws-core
Version: 0.2.41
Summary: Core package for interfacing with AWS
Author: services
Author-email: services@rydeas.com
Requires-Python: >=3.12,<3.13
Classifier: Programming Language :: Python :: 3
Classifier: Programming Language :: Python :: 3.12
Requires-Dist: boto3 (>=1.35.44,<2.0.0)
Requires-Dist: colorama (>=0.4.6,<0.5.0)
Requires-Dist: coverage (>=7.6.4,<8.0.0)
Requires-Dist: httpx (>=0.27.2,<0.28.0)
Requires-Dist: python-dotenv (>=1.0.1,<2.0.0)
Requires-Dist: respx (>=0.21.1,<0.22.0)
Requires-Dist: structlog (>=24.4.0,<25.0.0)
